my_own_package/__init__.py
alina_first_package-0.2.0.dist-info/METADATA
alina_first_package-0.2.0.dist-info/WHEEL
alina_first_package-0.2.0.dist-info/top_level.txt
alina_first_package-0.2.0.dist-info/RECORD
