Metadata-Version: 2.1
Name: alina-first-package
Version: 0.2.0
Summary: This is my first package
Home-page: UNKNOWN
Author: alina
Author-email: alina0515@yahoo.com
License: UNKNOWN
Platform: UNKNOWN
